djaodjin_survey-0.17.3.dist-info/licenses/LICENSE.txt
survey/__init__.py
survey/admin.py
survey/compat.py
survey/docs.py
survey/filters.py
survey/forms.py
survey/helpers.py
survey/mixins.py
survey/models.py
survey/pagination.py
survey/queries.py
survey/settings.py
survey/signals.py
survey/utils.py
survey/api/__init__.py
survey/api/base.py
survey/api/campaigns.py
survey/api/matrix.py
survey/api/metrics.py
survey/api/portfolios.py
survey/api/sample.py
survey/api/serializers.py
survey/api/serializers_overrides.py
survey/api/units.py
survey/management/__init__.py
survey/management/commands/__init__.py
survey/management/commands/expire_optins.py
survey/static/css/matrix-chart.css
survey/static/js/djaodjin-categorize.js
survey/static/js/djaodjin-matrix.js
survey/static/js/djaodjin-resources-vue.js
survey/static/js/djaodjin-set.js
survey/static/js/djaodjin-survey-vue.js
survey/static/js/djaodjin-survey.js
survey/static/js/matrix-chart.js
survey/templates/survey/answer_form.html
survey/templates/survey/campaign_form.html
survey/templates/survey/categorize.html
survey/templates/survey/portfolios.html
survey/templates/survey/question_form.html
survey/templates/survey/question_list.html
survey/templates/survey/respondent_list.html
survey/templates/survey/result.html
survey/templates/survey/result_quizz.html
survey/templates/survey/sample_create.html
survey/templates/survey/sample_update.html
survey/templates/survey/send.html
survey/templates/survey/campaigns/index.html
survey/templates/survey/matrix/compare.html
survey/templates/survey/matrix/index.html
survey/templates/survey/matrix/matrix.html
survey/templatetags/__init__.py
survey/templatetags/survey_tags.py
survey/urls/__init__.py
survey/urls/api/__init__.py
survey/urls/api/benchmarks.py
survey/urls/api/campaigns.py
survey/urls/api/filters.py
survey/urls/api/matrix.py
survey/urls/api/metrics.py
survey/urls/api/noauth.py
survey/urls/api/portfolios.py
survey/urls/api/sample/__init__.py
survey/urls/api/sample/reset.py
survey/urls/api/sample/update.py
djaodjin_survey-0.17.3.dist-info/METADATA
djaodjin_survey-0.17.3.dist-info/WHEEL
djaodjin_survey-0.17.3.dist-info/top_level.txt
djaodjin_survey-0.17.3.dist-info/RECORD
