Metadata-Version: 2.4
Name: djaodjin-survey
Version: 0.17.3
Summary: Django app for qualitative and quantitative surveys
Author-email: The DjaoDjin Team <help@djaodjin.com>
Maintainer-email: The DjaoDjin Team <help@djaodjin.com>
License: BSD-2-Clause
Project-URL: repository, https://github.com/djaodjin/djaodjin-survey
Project-URL: documentation, https://djaodjin-survey.readthedocs.io/
Project-URL: changelog, https://github.com/djaodjin/djaodjin-survey/changelog
Keywords: survey,assessment,census
Classifier: Framework :: Django
Classifier: Environment :: Web Environment
Classifier: Programming Language :: Python
Classifier: License :: OSI Approved :: BSD License
Requires-Python: >=3.7
License-File: LICENSE.txt
Requires-Dist: Django>=2.2
Requires-Dist: djangorestframework>=3.9
Requires-Dist: monotonic>=1.1
Requires-Dist: python-dateutil>=2.2
Dynamic: license-file
